{
    "name": "champion",
    "archetype": [
        "fighter"
    ],
    "general": {
        "lpMult": 3,
        "innate": [
            {
                "name": "life points",
                "level": 1,
                "gain": 15
            },
            {
                "name": "initiative",
                "level": 2,
                "gain": 1
            }
        ]
    },
    "martial": {
        "limit": 60,
        "strike": 4,
        "block": 4,
        "dodge": 4,
        "wearArmor": 4,
        "kiPoint": 2,
        "chakra": 2,
        "innate": [
            {
                "name": "spirit knowledge",
                "level": 1,
                "gain": 3
            },
            {
                "name": "strike",
                "level": 2,
                "gain": 1,
                "max": 5
            },
            {
                "name": "block",
                "level": 2,
                "gain": 1,
                "max": 5
            },
            {
                "name": "wear armor",
                "level": 2,
                "gain": 1
            }
        ]
    },
    "magic": {
        "limit": 50,
        "manaPoint": 3,
        "mAcc": 7,
        "mRec": 3,
        "mPrj": 5,
        "summon": 5,
        "control": 5,
        "banish": 5,
        "innate": [
            {
                "name": "mana",
                "level": 1,
                "gain": 5
            }
        ]
    },
    "manifest": {
        "limit": 50,
        "pPoint": 2,
        "pPrj": 5,
        "innate": [
            {
                "name": "phenom point",
                "level": 3,
                "gain": 1
            }
        ]
    },
    "secondary": {
        "exertion": 4,
        "social": 4,
        "perception": 4,
        "intellectual": 5,
        "vigor": 4,
        "subterfuge": 4,
        "creative": 4,
        "trade":4,
        "innate": [
            {
                "name": "athletics",
                "level": 1,
                "gain": 1
            },
            {
                "name": "feats of strength",
                "level": 1,
                "gain": 2
            }
        ],
        "reduced": [
            {
                "name": "feats of strength",
                "cost": 3,
                "gain": 1
            }
        ]
    }
}