[
    {
        "name": "General Slot",
        "type": "slot",
        "level": 4,
        "slot": "10"
    },
    {
        "name": "General Slot",
        "type": "slot",
        "level": 14,
        "slot": "20"
    },
    {
        "name": "General Slot",
        "type": "slot",
        "level": 24,
        "slot": "30"
    },
    {
        "name": "General Slot",
        "type": "slot",
        "level": 34,
        "slot": "40"
    },
    {
        "name": "General Slot",
        "type": "slot",
        "level": 44,
        "slot": "50"
    },
    {
        "name": "General Slot",
        "type": "slot",
        "level": 54,
        "slot": "60"
    },
    {
        "name": "General Slot",
        "type": "slot",
        "level": 64,
        "slot": "70"
    },
    {
        "name": "General Slot",
        "type": "slot",
        "level": 74,
        "slot": "80"
    },
    {
        "name": "General Slot",
        "type": "slot",
        "level": 84,
        "slot": "90"
    },
    {
        "name": "General Slot",
        "type": "slot",
        "level": 94,
        "slot": "100"
    },
    {
        "name": "Minor Creation",
        "type": "path",
        "level": 2,
        "power": [
            "automatic"
        ],
        "action": "active",
        "maintTime": "turn",
        "tags": [],
        "description": [
            "You create a number of simple objects. Each object cannot have more than 2 Presence."
        ],
        "degree": {
            "base": {
                "mana": 30,
                "int": 5,
                "maint": 5,
                "effect": [
                    "1 object"
                ]
            },
            "intermediate": {
                "mana": 80,
                "int": 8,
                "maint": 10,
                "effect": [
                    "4 objects"
                ]
            },
            "advanced": {
                "mana": 100,
                "int": 10,
                "maint": 10,
                "effect": [
                    "8 objects"
                ]
            },
            "arcane": {
                "mana": 120,
                "int": 12,
                "maint": 15,
                "effect": [
                    "12 objects"
                ]
            }
        }
    },
    {
        "name": "Reconstruct",
        "type": "path",
        "level": 6,
        "power": [
            "automatic"
        ],
        "action": "active",
        "maintTime": "no",
        "tags": [
            "affectable presence"
        ],
        "description": [
            "An entity of your choice whose total Presence is no greater than the listed value begins to reassemble from the parts nearby. If there are some parts missing, you can substitute a similar amount of raw material to recreate a simple part. Once the spell is cast, the reconstruction takes a 1 minute per point of Presence."
        ],
        "degree": {
            "base": {
                "mana": 40,
                "int": 5,
                "maint": 0,
                "effect": [
                    "Presence 2"
                ]
            },
            "intermediate": {
                "mana": 140,
                "int": 8,
                "maint": 0,
                "effect": [
                    "Presence 6"
                ]
            },
            "advanced": {
                "mana": 200,
                "int": 10,
                "maint": 0,
                "effect": [
                    "Presence 10"
                ]
            },
            "arcane": {
                "mana": 280,
                "int": 12,
                "maint": 0,
                "effect": [
                    "Presence 12"
                ]
            }
        }
    },
    {
        "name": "Create Intensity",
        "type": "path",
        "level": 8,
        "power": [
            "automatic"
        ],
        "action": "active",
        "maintTime": "turn",
        "tags": [
            "intensity"
        ],
        "description": [
            "You create intensities of Heat, Cold, Electricity, or Light."
        ],
        "degree": {
            "base": {
                "mana": 40,
                "int": 5,
                "maint": 5,
                "effect": [
                    "1 intensity"
                ]
            },
            "intermediate": {
                "mana": 150,
                "int": 8,
                "maint": 15,
                "effect": [
                    "5 intensities"
                ]
            },
            "advanced": {
                "mana": 200,
                "int": 10,
                "maint": 20,
                "effect": [
                    "10 intensities"
                ]
            },
            "arcane": {
                "mana": 250,
                "int": 12,
                "maint": 25,
                "effect": [
                    "20 intensities"
                ]
            }
        }
    },
    {
        "name": "Regeneration",
        "type": "path",
        "level": 10,
        "power": [
            "automatic"
        ],
        "action": "active",
        "maintTime": "day",
        "tags": [],
        "description": [
            "An entity of your choice gains a natural Final Regeneration Value. If the target's Regeneration is greater, than the spell has no effect."
        ],
        "degree": {
            "base": {
                "mana": 60,
                "int": 6,
                "maint": 10,
                "effect": [
                    "Regeneration 4"
                ]
            },
            "intermediate": {
                "mana": 100,
                "int": 9,
                "maint": 10,
                "effect": [
                    "Regeneration 6"
                ]
            },
            "advanced": {
                "mana": 150,
                "int": 12,
                "maint": 15,
                "effect": [
                    "Regeneration 8"
                ]
            },
            "arcane": {
                "mana": 250,
                "int": 15,
                "maint": 15,
                "effect": [
                    "Regeneration 10"
                ]
            }
        }
    },
    {
        "name": "Basic Modification",
        "type": "path",
        "level": 12,
        "power": [
            "automatic"
        ],
        "action": "active",
        "maintTime": "turn",
        "tags": [],
        "description": [
            "An object of your choice whose total Presence is no greater than the listed value changes. The new form's Presence must be no greater than its original Presence."
        ],
        "degree": {
            "base": {
                "mana": 60,
                "int": 6,
                "maint": 5,
                "effect": [
                    "Presence 2"
                ]
            },
            "intermediate": {
                "mana": 90,
                "int": 9,
                "maint": 5,
                "effect": [
                    "Presence 3"
                ]
            },
            "advanced": {
                "mana": 120,
                "int": 12,
                "maint": 5,
                "effect": [
                    "Presence 4"
                ]
            },
            "arcane": {
                "mana": 150,
                "int": 15,
                "maint": 10,
                "effect": [
                    "Presence 5"
                ]
            }
        }
    },
    {
        "name": "Increase Resistance",
        "type": "path",
        "level": 16,
        "power": [
            "automatic"
        ],
        "action": "active",
        "maintTime": "day",
        "tags": [],
        "description": [
            "An entity of your choice gains a power bonus to their Phr, IR, SR, and MR."
        ],
        "degree": {
            "base": {
                "mana": 80,
                "int": 8,
                "maint": 15,
                "effect": [
                    "`+1` bonus"
                ]
            },
            "intermediate": {
                "mana": 120,
                "int": 10,
                "maint": 20,
                "effect": [
                    "`+2` bonus"
                ]
            },
            "advanced": {
                "mana": 150,
                "int": 14,
                "maint": 30,
                "effect": [
                    "`+3` bonus"
                ]
            },
            "arcane": {
                "mana": 200,
                "int": 18,
                "maint": 40,
                "effect": [
                    "`+4` bonus"
                ]
            }
        }
    },
    {
        "name": "Royal Shield",
        "type": "path",
        "level": 18,
        "power": [
            "defense"
        ],
        "action": "swift",
        "maintTime": "turn",
        "tags": [],
        "description": [
            "You create a supernatural barrier with the listed Life Points. This barrier possess the Imbued trait."
        ],
        "degree": {
            "base": {
                "mana": 40,
                "int": 6,
                "maint": 0,
                "effect": [
                    "500 Life Points"
                ]
            },
            "intermediate": {
                "mana": 150,
                "int": 9,
                "maint": 0,
                "effect": [
                    "3000 Life Points"
                ]
            },
            "advanced": {
                "mana": 260,
                "int": 12,
                "maint": 0,
                "effect": [
                    "5000 Life Points"
                ]
            },
            "arcane": {
                "mana": 400,
                "int": 15,
                "maint": 0,
                "effect": [
                    "10,000 Life Points"
                ]
            }
        }
    },
    {
        "name": "Heal",
        "type": "path",
        "level": 20,
        "power": [
            "automatic"
        ],
        "action": "active",
        "maintTime": "no",
        "tags": [],
        "description": [
            "An entity of your choice recovers Life Points and reduces its degrees of Pain. This spell cannot restore damaged limbs. eliminate Pain."
        ],
        "degree": {
            "base": {
                "mana": 80,
                "int": 8,
                "maint": 0,
                "effect": [
                    "50 Life Points",
                    "Reduce Pain by 1"
                ]
            },
            "intermediate": {
                "mana": 120,
                "int": 10,
                "maint": 0,
                "effect": [
                    "150 Life Points",
                    "Reduce Pain by 5"
                ]
            },
            "advanced": {
                "mana": 150,
                "int": 14,
                "maint": 0,
                "effect": [
                    "250 Life Points",
                    "Reduce Pain by 10"
                ]
            },
            "arcane": {
                "mana": 200,
                "int": 18,
                "maint": 0,
                "effect": [
                    "250 Life Points",
                    "Reduce Pain by 15"
                ]
            }
        }
    },
    {
        "name": "Negate Damage",
        "type": "path",
        "level": 22,
        "power": [
            "automatic"
        ],
        "action": "active",
        "maintTime": "day",
        "tags": [],
        "description": [
            "An entity of your choice gains a Base Damage Negate against the Physical Damage Group. This BDN can be overcome with the Imbued trait."
        ],
        "degree": {
            "base": {
                "mana": 60,
                "int": 6,
                "maint": 10,
                "effect": [
                    "Base Damage Negate 3"
                ]
            },
            "intermediate": {
                "mana": 90,
                "int": 9,
                "maint": 10,
                "effect": [
                    "Base Damage Negate 5"
                ]
            },
            "advanced": {
                "mana": 120,
                "int": 12,
                "maint": 15,
                "effect": [
                    "Base Damage Negate 8"
                ]
            },
            "arcane": {
                "mana": 150,
                "int": 15,
                "maint": 15,
                "effect": [
                    "Base Damage Negate 10"
                ]
            }
        }
    },
    {
        "name": "Create Homunculus",
        "type": "path",
        "level": 26,
        "power": [
            "automatic"
        ],
        "action": "active",
        "maintTime": "turn",
        "tags": [],
        "description": [
            "You create monad creatures. The creature's level is 0 and must follow the rules for monad creatures. Each homunculus created can have different profiles. The creature is created with the following rules:",
            {
                "type": "list",
                "items": [
                    "The creatures are mana elementals with Nornir 5.",
                    "No Characteristic or Skill can have a Final Value greater than 5.",
                    "The creature's size is reduced by 2 and it cannot choose the Uncommon Size feature.",
                    "No Intellectual or Creative Skill's Final Value can be greater than your Final Value."
                ]
            },
            "No matter how many creatures this spell creates, they count as a single creature for the purpose of determining the maximum level of other monad creatures."
        ],
        "degree": {
            "base": {
                "mana": 60,
                "int": 6,
                "maint": 10,
                "effect": [
                    "1 homunculus"
                ]
            },
            "intermediate": {
                "mana": 80,
                "int": 9,
                "maint": 20,
                "effect": [
                    "10 homunculi"
                ]
            },
            "advanced": {
                "mana": 250,
                "int": 12,
                "maint": 25,
                "effect": [
                    "25 homunculi"
                ]
            },
            "arcane": {
                "mana": 350,
                "int": 15,
                "maint": 35,
                "effect": [
                    "100 homunculi"
                ]
            }
        }
    },
    {
        "name": "Minor Change",
        "type": "path",
        "level": 28,
        "power": [
            "effect"
        ],
        "action": "active",
        "maintTime": "day",
        "tags": [],
        "description": [
            "You make an Offensive Roll against an entity. On a hit, a target must make a SR Check; a target can choose to fail.",
            "A target that fails the Resistance Check has its appearance changed. A target can repeat the Resistance Check on the End Phase after a number of minutes have passed equal to their Degree of Failure on the previous Check.",
            "The change is limited to superficial appearances. For example, you could cause a boulder to appear to be covered in moss. A living target can have its size modified by 2 points but anything it is wearing does not change with it, since they are not targeted."
        ],
        "degree": {
            "base": {
                "mana": 60,
                "int": 6,
                "maint": 10,
                "effect": [
                    "SR 8",
                    "Presence 6"
                ]
            },
            "intermediate": {
                "mana": 90,
                "int": 9,
                "maint": 10,
                "effect": [
                    "SR 10",
                    "Presence 9"
                ]
            },
            "advanced": {
                "mana": 150,
                "int": 12,
                "maint": 15,
                "effect": [
                    "SR 12",
                    "Presence 12"
                ]
            },
            "arcane": {
                "mana": 250,
                "int": 15,
                "maint": 25,
                "effect": [
                    "SR 14",
                    "Presence 18"
                ]
            }
        }
    },
    {
        "name": "Imitate",
        "type": "path",
        "level": 30,
        "power": [
            "effect",
            "automatic"
        ],
        "action": "active",
        "maintTime": "day",
        "tags": [],
        "description": [
            "An object you are in contact with and whose total Presence is no greater than the listed value is duplicated. The duplicate of the target retains all the qualities of the original, including supernatural ones. The duplicate object has the same Presence as the original."
        ],
        "degree": {
            "base": {
                "mana": 100,
                "int": 6,
                "maint": 5,
                "effect": [
                    "Presence 3"
                ]
            },
            "intermediate": {
                "mana": 200,
                "int": 9,
                "maint": 10,
                "effect": [
                    "Presence 8"
                ]
            },
            "advanced": {
                "mana": 300,
                "int": 12,
                "maint": 15,
                "effect": [
                    "Presence 12"
                ]
            },
            "arcane": {
                "mana": 400,
                "int": 15,
                "maint": 20,
                "effect": [
                    "Presence 16"
                ]
            }
        }
    },
    {
        "name": "Immunity",
        "type": "path",
        "level": 32,
        "power": [
            "automatic"
        ],
        "action": "active",
        "maintTime": "day",
        "tags": [],
        "description": [
            "Choose a single entity to target and one elemental intensity. The target gains the listed intensity immunity to the choosen elemental."
        ],
        "degree": {
            "base": {
                "mana": 80,
                "int": 6,
                "maint": 10,
                "effect": [
                    "4 intensities"
                ]
            },
            "intermediate": {
                "mana": 180,
                "int": 9,
                "maint": 20,
                "effect": [
                    "16 intensities"
                ]
            },
            "advanced": {
                "mana": 240,
                "int": 12,
                "maint": 25,
                "effect": [
                    "24 intensities"
                ]
            },
            "arcane": {
                "mana": 300,
                "int": 15,
                "maint": 30,
                "effect": [
                    "36 intensities"
                ]
            }
        }
    },
    {
        "name": "Reduce Damage",
        "type": "path",
        "level": 36,
        "power": [
            "automatic"
        ],
        "action": "reaction",
        "maintTime": "no",
        "tags": [],
        "description": [
            "You can cast this spell when an attack is declared but before any dice are rolled. You reduce the Base Damage of the triggering attack."
        ],
        "degree": {
            "base": {
                "mana": 80,
                "int": 8,
                "maint": 0,
                "effect": [
                    "Base Damage -4"
                ]
            },
            "intermediate": {
                "mana": 120,
                "int": 10,
                "maint": 0,
                "effect": [
                    "Base Damage -6"
                ]
            },
            "advanced": {
                "mana": 160,
                "int": 14,
                "maint": 0,
                "effect": [
                    "Base Damage -8"
                ]
            },
            "arcane": {
                "mana": 240,
                "int": 18,
                "maint": 0,
                "effect": [
                    "Base Damage -10"
                ]
            }
        }
    },
    {
        "name": "Physical Control",
        "type": "path",
        "level": 38,
        "power": [
            "effect"
        ],
        "action": "active",
        "maintTime": "turn",
        "tags": [
            "physical control"
        ],
        "description": [
            "You gain physical control over a creature. Choose a single creature to target. The target must succeed a SR Check or have its physical actions controlled by you. The target can repeat the Resistance Check on the End Phase after a number of hours have passed equal to their Degree of Failure."
        ],
        "degree": {
            "base": {
                "mana": 120,
                "int": 6,
                "maint": 25,
                "effect": [
                    "SR 8"
                ]
            },
            "intermediate": {
                "mana": 180,
                "int": 9,
                "maint": 40,
                "effect": [
                    "SR 10"
                ]
            },
            "advanced": {
                "mana": 240,
                "int": 12,
                "maint": 50,
                "effect": [
                    "SR 12"
                ]
            },
            "arcane": {
                "mana": 300,
                "int": 15,
                "maint": 60,
                "effect": [
                    "SR 14"
                ]
            }
        }
    },
    {
        "name": "Raise Skill",
        "type": "path",
        "level": 40,
        "power": [
            "automatic"
        ],
        "action": "active",
        "maintTime": "turn",
        "tags": [],
        "description": [
            "Choose a single entity to target. The target gains the listed number of points that they can distribute to any trained Secondary Skill as a power bonus."
        ],
        "degree": {
            "base": {
                "mana": 80,
                "int": 6,
                "maint": 5,
                "effect": [
                    "5 points"
                ]
            },
            "intermediate": {
                "mana": 180,
                "int": 9,
                "maint": 10,
                "effect": [
                    "15 points"
                ]
            },
            "advanced": {
                "mana": 280,
                "int": 12,
                "maint": 15,
                "effect": [
                    "25 points"
                ]
            },
            "arcane": {
                "mana": 350,
                "int": 15,
                "maint": 20,
                "effect": [
                    "40 points"
                ]
            }
        }
    },
    {
        "name": "Fuse",
        "type": "path",
        "level": 42,
        "power": [
            "effect"
        ],
        "action": "active",
        "maintTime": "turn",
        "tags": [],
        "description": [
            "Choose two entities to target whose total Presence is no greater than the listed Presence and who are within 5 feet of each other. The targets must succeed a SR Check or be fused into a single new entity. A creature can willingly accept the effects of this spell.",
            {
                "name": "Case: two creatures",
                "type": "entries",
                "entries": [
                    "This new creature possess the abilities and features of both targets. You can designate which Base Values, innate bonuses, natural bonuses, and other abilities come from which target. For example, if you fuse a martial artist and a manifester, you can give the new creature the physical Characteristics of the martial artitist and the mental Characteristics of the mentalist. The new creature can fight unarmed and use phenom with ease.",
                    "Control of the resulting creature is determined by an Opposed Willpower Check between the targets. The Opposed Willpower Check can be repeated on the End Phase after a number of hours have passed equal to the Degree of Difference. If the DoD is less than 10, then the personality of the loser will influence the actions of the new creature."
                ]
            },
            {
                "name": "Case: one creature and one object",
                "type": "entries",
                "entries": [
                    "The Game Master can grant the new creature features related to the fused object."
                ]
            },
            {
                "name": "Case: two objects",
                "type": "entries",
                "entries": [
                    "You can the Game Master can determine what the new object will be able to do, based on the original objects."
                ]
            },
            "When the spell ends, the targets return to the state they were in before the spell. The death of the new creature, or the breaking of the new object, causes both targets to die."
        ],
        "degree": {
            "base": {
                "mana": 140,
                "int": 8,
                "maint": 15,
                "effect": [
                    "SR 8",
                    "Presence 8"
                ]
            },
            "intermediate": {
                "mana": 180,
                "int": 10,
                "maint": 20,
                "effect": [
                    "SR 10",
                    "Presence 12"
                ]
            },
            "advanced": {
                "mana": 240,
                "int": 14,
                "maint": 25,
                "effect": [
                    "SR 12",
                    "Presence 16"
                ]
            },
            "arcane": {
                "mana": 0,
                "int": 18,
                "maint": 30,
                "effect": [
                    "SR 14",
                    "Presence 20"
                ]
            }
        }
    },
    {
        "name": "Create Memories",
        "type": "path",
        "level": 46,
        "power": [
            "effect"
        ],
        "action": "active",
        "maintTime": "no",
        "tags": [],
        "description": [
            "You can implant memories into a creature. Choose a single creature to target. The target must succeed a SR or MR Check or you creature memories that they accept as real. The memories to plant must be determined before the Resistance Check is made. The target can repeat the Resistance Check whenever they are given a reason to doubt the planted memories.",
            "Memories that are go against the nature of the creature have their Resistance Check difficulty reduced by 6 points."
        ],
        "degree": {
            "base": {
                "mana": 140,
                "int": 8,
                "maint": 0,
                "effect": [
                    "SR or MR 10"
                ]
            },
            "intermediate": {
                "mana": 180,
                "int": 10,
                "maint": 0,
                "effect": [
                    "SR or MR 12"
                ]
            },
            "advanced": {
                "mana": 240,
                "int": 14,
                "maint": 0,
                "effect": [
                    "SR or MR 16"
                ]
            },
            "arcane": {
                "mana": 350,
                "int": 18,
                "maint": 0,
                "effect": [
                    "SR or MR 20"
                ]
            }
        }
    },
    {
        "name": "Recover",
        "type": "path",
        "level": 48,
        "power": [
            "automatic"
        ],
        "action": "active",
        "maintTime": "no",
        "tags": [],
        "description": [
            "Choose a single creature to target. The target regains the listed number of Life Points. This spell removes all degrees of Pain caused by natural means."
        ],
        "degree": {
            "base": {
                "mana": 250,
                "int": 8,
                "maint": 0,
                "effect": [
                    "500 Life Points"
                ]
            },
            "intermediate": {
                "mana": 300,
                "int": 10,
                "maint": 0,
                "effect": [
                    "750 Life Points"
                ]
            },
            "advanced": {
                "mana": 350,
                "int": 14,
                "maint": 0,
                "effect": [
                    "1000 Life Points"
                ]
            },
            "arcane": {
                "mana": 400,
                "int": 18,
                "maint": 0,
                "effect": [
                    "1500 Life Points"
                ]
            }
        }
    },
    {
        "name": "Aquire Power",
        "type": "path",
        "level": 50,
        "power": [
            "automatic"
        ],
        "action": "active",
        "maintTime": "turn",
        "tags": [],
        "description": [
            "Choose a single entity to target. The target can temporarily gain creature features whose total XP cost is no greater than the listed amount. The target can buy features as a Nornir 25 creature and their phsyical shape will change as approriat. For example, if the target gains a natural Flight Value, they would sprout wings."
        ],
        "degree": {
            "base": {
                "mana": 100,
                "int": 8,
                "maint": 20,
                "effect": [
                    "10 XP"
                ]
            },
            "intermediate": {
                "mana": 200,
                "int": 10,
                "maint": 40,
                "effect": [
                    "20 XP"
                ]
            },
            "advanced": {
                "mana": 300,
                "int": 14,
                "maint": 60,
                "effect": [
                    "30 XP"
                ]
            },
            "arcane": {
                "mana": 400,
                "int": 18,
                "maint": 80,
                "effect": [
                    "40 XP"
                ]
            }
        }
    },
    {
        "name": "Create Creature",
        "type": "path",
        "level": 52,
        "power": [
            "automatic"
        ],
        "action": "active",
        "maintTime": "turn",
        "tags": [
            "power creature"
        ],
        "description": [
            "You create a creature out of thin air. The creature's maximum level is listed and follows the rules for creatures created by powers. Additionally, the following rules apply:",
            {
                "type": "list",
                "items": [
                    "The creature is a monad with Nornir 20.",
                    "The creature can never be given a soul."
                ]
            }
        ],
        "degree": {
            "base": {
                "mana": 80,
                "int": 10,
                "maint": 10,
                "effect": [
                    "Level 2"
                ]
            },
            "intermediate": {
                "mana": 120,
                "int": 12,
                "maint": 15,
                "effect": [
                    "Level 4"
                ]
            },
            "advanced": {
                "mana": 250,
                "int": 16,
                "maint": 25,
                "effect": [
                    "Level 8"
                ]
            },
            "arcane": {
                "mana": 500,
                "int": 20,
                "maint": 50,
                "effect": [
                    "Level 12"
                ]
            }
        }
    },
    {
        "name": "Protective Aura",
        "type": "path",
        "level": 56,
        "power": [
            "automatic"
        ],
        "action": "active",
        "maintTime": "turn",
        "tags": [],
        "description": [
            "All entities you choose within the area gain a power bonus to all PhR, IR, SR, and MR Checks. You must be aware of an entity to grant the bonus."
        ],
        "degree": {
            "base": {
                "mana": 120,
                "int": 8,
                "maint": 10,
                "effect": [
                    "300-foot radius",
                    "+2 bonus"
                ]
            },
            "intermediate": {
                "mana": 180,
                "int": 10,
                "maint": 15,
                "effect": [
                    "1000-foot radius",
                    "+5 bonus"
                ]
            },
            "advanced": {
                "mana": 240,
                "int": 14,
                "maint": 25,
                "effect": [
                    "3,000-foot radius",
                    "+8 bonus"
                ]
            },
            "arcane": {
                "mana": 350,
                "int": 18,
                "maint": 35,
                "effect": [
                    "1-mi radius",
                    "+12 bonus"
                ]
            }
        }
    },
    {
        "name": "Spiritual Standstill",
        "type": "path",
        "level": 58,
        "power": [
            "effect"
        ],
        "action": "active",
        "maintTime": "turn",
        "tags": [],
        "description": [
            "Choose a single entity to target. The target must succeed a SR Check or become spiritually immutable. The target can repeat the Resistance Check on the End Phase after a number of rounds have passed equal to their Degree of Failure.",
            "Any mental state affecting the target at the time of casting will not change. The target ignores any further mental state changes. The nature of the target cannot be changed either."
        ],
        "degree": {
            "base": {
                "mana": 150,
                "int": 8,
                "maint": 15,
                "effect": [
                    "SR 10"
                ]
            },
            "intermediate": {
                "mana": 200,
                "int": 10,
                "maint": 20,
                "effect": [
                    "SR 12"
                ]
            },
            "advanced": {
                "mana": 250,
                "int": 14,
                "maint": 25,
                "effect": [
                    "SR 14"
                ]
            },
            "arcane": {
                "mana": 300,
                "int": 18,
                "maint": 30,
                "effect": [
                    "SR 16"
                ]
            }
        }
    },
    {
        "name": "Perfect Shield",
        "type": "path",
        "level": 60,
        "power": [
            "defense"
        ],
        "action": "active",
        "maintTime": "day",
        "tags": [],
        "description": [
            "You create a supernatural barrier with the listed Life Points. If the barrier is not broken, it regains all its Life Points at the start of the End Phase.",
            "Unlike most defensive powers, this spell is cast as an Active Action."
        ],
        "degree": {
            "base": {
                "mana": 150,
                "int": 8,
                "maint": 15,
                "effect": [
                    "100 Life Points"
                ]
            },
            "intermediate": {
                "mana": 200,
                "int": 10,
                "maint": 20,
                "effect": [
                    "250 Life Points"
                ]
            },
            "advanced": {
                "mana": 300,
                "int": 14,
                "maint": 30,
                "effect": [
                    "500 Life Points"
                ]
            },
            "arcane": {
                "mana": 400,
                "int": 18,
                "maint": 40,
                "effect": [
                    "1000 Life Points"
                ]
            }
        }
    },
    {
        "name": "Vitality",
        "type": "path",
        "level": 62,
        "power": [
            "automatic"
        ],
        "action": "active",
        "maintTime": "day",
        "tags": [],
        "description": [
            "Choose a single entity to target. The target gains a power bonus to their maximum Life Points. When the spell ends, the targets current and maximum amount are reduced by the amount gained.",
            "A target with the Rex Damage Role mutliplies the bonus by their Rex Multiplier."
        ],
        "degree": {
            "base": {
                "mana": 150,
                "int": 8,
                "maint": 15,
                "effect": [
                    "Life Point max +50"
                ]
            },
            "intermediate": {
                "mana": 200,
                "int": 10,
                "maint": 20,
                "effect": [
                    "Life Point max +75"
                ]
            },
            "advanced": {
                "mana": 250,
                "int": 14,
                "maint": 25,
                "effect": [
                    "Life Point max +100"
                ]
            },
            "arcane": {
                "mana": 350,
                "int": 18,
                "maint": 35,
                "effect": [
                    "Life Point max +150"
                ]
            }
        }
    },
    {
        "name": "Complete Creation",
        "type": "path",
        "level": 66,
        "power": [
            "automatic"
        ],
        "action": "active",
        "maintTime": "day",
        "tags": [],
        "description": [
            "You create object whose total Presence is no greater than the listed Presence or twice your Presence. The object must appear in a location that is logical for it, according to its nature. For example, you could not create a boulder in mid air, but a cloud could appear in the sky."
        ],
        "degree": {
            "base": {
                "mana": 150,
                "int": 8,
                "maint": 15,
                "effect": [
                    "Presence 4"
                ]
            },
            "intermediate": {
                "mana": 200,
                "int": 10,
                "maint": 20,
                "effect": [
                    "Presence 8"
                ]
            },
            "advanced": {
                "mana": 300,
                "int": 14,
                "maint": 30,
                "effect": [
                    "Presence 12"
                ]
            },
            "arcane": {
                "mana": 400,
                "int": 18,
                "maint": 40,
                "effect": [
                    "Presence 16"
                ]
            }
        }
    },
    {
        "name": "Reinforce Magic",
        "type": "path",
        "level": 68,
        "power": [
            "automatic"
        ],
        "action": "reaction",
        "maintTime": "turn",
        "tags": [],
        "description": [
            "You can cast this spell when you cast another spell. The triggering spell has the following benefits:",
            {
                "type": "list",
                "items": [
                    "Any SR Check increases the difficulty by 2",
                    "Any Base Damage is increased by 50%",
                    "Supernatural barrier's increase Life Points by 50%",
                    "All other numbers increase by 20%, round down, except for Nornir."
                ]
            },
            "You must pay the maintaince of the triggering spell and this spell. If either spell ends, they both end."
        ],
        "degree": {
            "base": {
                "mana": 100,
                "int": 8,
                "maint": 10,
                "effect": [
                    "Base Degree spells"
                ]
            },
            "intermediate": {
                "mana": 200,
                "int": 10,
                "maint": 20,
                "effect": [
                    "Intermediate Degree spells"
                ]
            },
            "advanced": {
                "mana": 300,
                "int": 14,
                "maint": 30,
                "effect": [
                    "Advanced Degree spells"
                ]
            },
            "arcane": {
                "mana": 400,
                "int": 18,
                "maint": 40,
                "effect": [
                    "Arcane Degree spells"
                ]
            }
        }
    },
    {
        "name": "Transmute",
        "type": "path",
        "level": 70,
        "power": [
            "effect"
        ],
        "action": "active",
        "maintTime": "turn",
        "tags": [],
        "description": [
            "Choose a single non-living object whose total Presence is no greater than the listed Presence. You convert the object into a completely different one with a similar Presence. If the target is supernatural, it can make a SR Check to resist the change."
        ],
        "degree": {
            "base": {
                "mana": 250,
                "int": 12,
                "maint": 0,
                "effect": [
                    "SR 12",
                    "Presence 5"
                ]
            },
            "intermediate": {
                "mana": 350,
                "int": 14,
                "maint": 0,
                "effect": [
                    "SR 16",
                    "Presence 10"
                ]
            },
            "advanced": {
                "mana": 500,
                "int": 18,
                "maint": 0,
                "effect": [
                    "SR 22",
                    "Presence 150"
                ]
            },
            "arcane": {
                "mana": 800,
                "int": 22,
                "maint": 0,
                "effect": [
                    "SR 26",
                    "Presence 20"
                ]
            }
        }
    },
    {
        "name": "Metamorphism",
        "type": "path",
        "level": 72,
        "power": [
            "automatic"
        ],
        "action": "active",
        "maintTime": "day",
        "tags": [],
        "description": [
            "Choose a single entity to target and a new form for the entity to take. The target must succeed a SR Check or be transformed into the new form. The new forms Presence can be no greater than the target's Presence.",
            "If the new form is a creature, the Game Master can grant certain features of a natural creature of Nornir 0. If the new form is an object, a creature remains alive."
        ],
        "degree": {
            "base": {
                "mana": 150,
                "int": 8,
                "maint": 10,
                "effect": [
                    "SR 10"
                ]
            },
            "intermediate": {
                "mana": 200,
                "int": 10,
                "maint": 10,
                "effect": [
                    "SR 12"
                ]
            },
            "advanced": {
                "mana": 250,
                "int": 14,
                "maint": 15,
                "effect": [
                    "SR 14"
                ]
            },
            "arcane": {
                "mana": 300,
                "int": 18,
                "maint": 20,
                "effect": [
                    "SR 16"
                ]
            }
        }
    },
    {
        "name": "Recreate",
        "type": "path",
        "level": 76,
        "power": [
            "automatic"
        ],
        "action": "active",
        "maintTime": "no",
        "tags": [],
        "description": [
            "Choose a number of entities whose total Presence is no greater than the listed Presence. You restore any damage or loss that target has, creatures regain all Life Points and objects are made whole. You can choose what to recreate, for example you could fix a missing arm but leave a broken leg. This spell also eliminates any lingering physical or spiritual effects.",
            "This spell does have some limitations. First it cannot restore a spirit to its body or recreate a lost body. Second, this spell only recreates something to its natural state. This cannot recreate something that never existed or something caused by aging.",
            "If the entity was damaged by a creature whose Nornir is 15 points higher than yours, the spell has no effect on the target."
        ],
        "degree": {
            "base": {
                "mana": 300,
                "int": 8,
                "maint": 0,
                "effect": [
                    "Presence 6"
                ]
            },
            "intermediate": {
                "mana": 500,
                "int": 10,
                "maint": 0,
                "effect": [
                    "Presence 12"
                ]
            },
            "advanced": {
                "mana": 750,
                "int": 14,
                "maint": 0,
                "effect": [
                    "Presence 18"
                ]
            },
            "arcane": {
                "mana": 1500,
                "int": 18,
                "maint": 0,
                "effect": [
                    "Presence 24"
                ]
            }
        }
    },
    {
        "name": "Create Being",
        "type": "path",
        "level": 78,
        "power": [
            "automatic"
        ],
        "action": "active",
        "maintTime": "day",
        "tags": [],
        "description": [
            "You create a creature out of thin air. The creature's maximum level is listed and follows the rules for creatures created by powers. Additionally, the following rules apply:",
            {
                "type": "list",
                "items": [
                    "The creature is a monad with Nornir 20."
                ]
            }
        ],
        "degree": {
            "base": {
                "mana": 250,
                "int": 14,
                "maint": 50,
                "effect": [
                    "Level 2"
                ]
            },
            "intermediate": {
                "mana": 400,
                "int": 16,
                "maint": 80,
                "effect": [
                    "Level 4"
                ]
            },
            "advanced": {
                "mana": 600,
                "int": 20,
                "maint": 120,
                "effect": [
                    "Level 8"
                ]
            },
            "arcane": {
                "mana": 1000,
                "int": 24,
                "maint": 200,
                "effect": [
                    "Level 12"
                ]
            }
        }
    },
    {
        "name": "Chimera",
        "type": "path",
        "level": 80,
        "power": [
            "automatic"
        ],
        "action": "active",
        "maintTime": "no",
        "tags": [],
        "description": [
            "Choose a single natural type creature to target. The target ceases being a natural being and becomes a Beyond the Veil creature with a Nornir of 25. Your level increases by the listed amount and you can choose a number of negative features granting you additional XP. All features gained as a result of this spell are dependant on the target's body. If the target ever loses their body, either by their spirit migrating or resurrection, all the effects of the spell end."
        ],
        "degree": {
            "base": {
                "mana": 250,
                "int": 12,
                "maint": 0,
                "effect": [
                    "Level +1",
                    "Up to 10 XP of negative features"
                ]
            },
            "intermediate": {
                "mana": 500,
                "int": 14,
                "maint": 0,
                "effect": [
                    "Level +2",
                    "Up to 20 XP of negative features"
                ]
            },
            "advanced": {
                "mana": 1000,
                "int": 18,
                "maint": 0,
                "effect": [
                    "Level +3",
                    "Up to 30 XP of negative features"
                ]
            },
            "arcane": {
                "mana": 2500,
                "int": 22,
                "maint": 0,
                "effect": [
                    "Level +4",
                    "Up to 40 XP of negative features"
                ]
            }
        }
    },
    {
        "name": "Zone of Safety",
        "type": "path",
        "level": 82,
        "power": [
            "trigger"
        ],
        "action": "active",
        "maintTime": "day",
        "tags": [],
        "description": [
            "You create an area where no entity can be harmed in any way by another entity. For example, a creature within the zone could not break down a door or step on a spider. Similarly, a projectile fired into the area would be unable to harm a creature inside the area. The exception to this is a creature can continue to cook and consume food that is already harvested or prepared.",
            "Any target can try to overcome the affect by making a SR Check. On a success, the target can act normally. The Resistance Check can be repeated on the End Phase after one day has passed. Even if the target leaves the area and reenters, the effect will persist. Additionally, the target can make a new Resistance Check whenever they take damage -- in this case the target also gains a `+2` deed bonus to the Resistance Check.",
            "This spell cannot select targets, even if another power would allow you to; everyone in the area is equally affected."
        ],
        "degree": {
            "base": {
                "mana": 350,
                "int": 12,
                "maint": 35,
                "effect": [
                    "100-foot radius",
                    "SR 14"
                ]
            },
            "intermediate": {
                "mana": 500,
                "int": 14,
                "maint": 50,
                "effect": [
                    "1500-foot radius",
                    "SR 18"
                ]
            },
            "advanced": {
                "mana": 800,
                "int": 18,
                "maint": 80,
                "effect": [
                    "1-mi radius",
                    "SR 22"
                ]
            },
            "arcane": {
                "mana": 1500,
                "int": 22,
                "maint": 150,
                "effect": [
                    "3-mi radius",
                    "SR 26"
                ]
            }
        }
    },
    {
        "name": "Maintain Magic",
        "type": "path",
        "level": 86,
        "power": [
            "automatic"
        ],
        "action": "active",
        "maintTime": "no",
        "tags": [],
        "description": [
            "Choose a single spell that you or a another creature are maintaining. The target spell gains a special Mana Pool that it will pull from to maintain itself.",
            "You can cast this spell multiple times per spell, giving it even more mana."
        ],
        "degree": {
            "base": {
                "mana": 250,
                "int": 10,
                "maint": 0,
                "effect": [
                    "500 mana"
                ]
            },
            "intermediate": {
                "mana": 500,
                "int": 12,
                "maint": 0,
                "effect": [
                    "2000 mana"
                ]
            },
            "advanced": {
                "mana": 1000,
                "int": 16,
                "maint": 0,
                "effect": [
                    "5000 mana"
                ]
            },
            "arcane": {
                "mana": 2000,
                "int": 20,
                "maint": 0,
                "effect": [
                    "10,000 mana"
                ]
            }
        }
    },
    {
        "name": "Provide Soul",
        "type": "path",
        "level": 88,
        "power": [
            "attack",
            "defense",
            "effect",
            "automatic",
            "trigger",
            "detection"
        ],
        "action": "active",
        "maintTime": "no",
        "tags": [],
        "description": [
            "You create a soul. You can place that soul within an entity whose Presence is no greater than the listed Presence. When a creature created from a power, such as Create Being, gains a soul, it severs all ties with their caster. The creature is no longer controlled by its caster and does not need to be maintained any more.",
            "Not all souls created by this spell are capable of entering a body. Each soul created has a one percent chance to be rejected or is automatically rejected if the body possess too much Presence. In this case, the soul lingers one minute before moving onto the Veil."
        ],
        "degree": {
            "base": {
                "mana": 500,
                "int": 14,
                "maint": 0,
                "effect": [
                    "Presence 3"
                ]
            },
            "intermediate": {
                "mana": 800,
                "int": 16,
                "maint": 0,
                "effect": [
                    "Presence 5"
                ]
            },
            "advanced": {
                "mana": 1200,
                "int": 12,
                "maint": 20,
                "effect": [
                    "Presence 8"
                ]
            },
            "arcane": {
                "mana": 2000,
                "int": 15,
                "maint": 24,
                "effect": [
                    "Presence 10"
                ]
            }
        }
    },
    {
        "name": "Greater Creation",
        "type": "path",
        "level": 90,
        "power": [
            "automatic"
        ],
        "action": "active",
        "maintTime": "day",
        "tags": [],
        "description": [
            "You gain a pool of Presence Points that you can use to create objects as an Active Action. Any object you create cannot have a Presence greater than the listed maximum Presence. Once the pool of Presence Points is used up, you cannot create anything else."
        ],
        "degree": {
            "base": {
                "mana": 400,
                "int": 10,
                "maint": 20,
                "effect": [
                    "50 Presence Points",
                    "Max Presence 10"
                ]
            },
            "intermediate": {
                "mana": 800,
                "int": 12,
                "maint": 25,
                "effect": [
                    "100 Presence Points",
                    "Max Presence 12"
                ]
            },
            "advanced": {
                "mana": 1200,
                "int": 16,
                "maint": 25,
                "effect": [
                    "200 Presence Points",
                    "Max Presence 14"
                ]
            },
            "arcane": {
                "mana": 1600,
                "int": 20,
                "maint": 30,
                "effect": [
                    "500 Presence Points",
                    "Max Presence 18"
                ]
            }
        }
    },
    {
        "name": "Eternal Magic",
        "type": "path",
        "level": 92,
        "power": [
            "automatic"
        ],
        "action": "active",
        "maintTime": "no",
        "tags": [],
        "description": [
            "Choose a single spell that you or a another creature are maintaining. If the targeted spell has a daily maintenance, it no longer requires any maintenance. If the spell has a per turn maintenance, it instead becomes daily."
        ],
        "degree": {
            "base": {
                "mana": 600,
                "int": 12,
                "maint": 0,
                "effect": [
                    "Base Degree spells"
                ]
            },
            "intermediate": {
                "mana": 1000,
                "int": 14,
                "maint": 0,
                "effect": [
                    "Intermediate Degree spells"
                ]
            },
            "advanced": {
                "mana": 2500,
                "int": 18,
                "maint": 0,
                "effect": [
                    "Advanced Degree spells"
                ]
            },
            "arcane": {
                "mana": 5000,
                "int": 22,
                "maint": 0,
                "effect": [
                    "Arcane Degree spells"
                ]
            }
        }
    },
    {
        "name": "Separate Worlds",
        "type": "path",
        "level": 96,
        "power": [
            "automatic"
        ],
        "action": "active",
        "maintTime": "day",
        "tags": [],
        "description": [
            "You create a breach in reality that is capable of separating the world into two parts. This separation cannot be perceived naturally, all visual planes are unable to sense the change. The wall itself can be made to have any appearance, from being invisible to being a large stone wall. Any attempt to see through the wall fails, no matter what power is used.",
            "Any attempt to move through the wall causes the creature to reappear at another point on the wall. This transport is not automatic, instead it occurs little by little as reality changes to steer you away. This failed navigation can be detected with a Zen (44) Notice Check.",
            "You can choose to lease passages, either two or one way and can require certain conditions to be meet. Alternatively, a Nornir 25 creature who is aware of the separated worlds and is navigating can make an SR Check to get through. A success also allows the creature to lead others through if they travel as a group. A creature who has failed can repeat the Resistance Check after a day has passed. A creature that has passed loses the ability to travel through the wall once they leave its border.",
            "The maximum volume that can be separated is listed."
        ],
        "degree": {
            "base": {
                "mana": 800,
                "int": 16,
                "maint": 40,
                "effect": [
                    "SR 12",
                    "50 cubic miles"
                ]
            },
            "intermediate": {
                "mana": 2500,
                "int": 20,
                "maint": 45,
                "effect": [
                    "SR 18",
                    "500 cubic miles"
                ]
            },
            "advanced": {
                "mana": 5000,
                "int": 24,
                "maint": 45,
                "effect": [
                    "SR 24",
                    "5000 cubic miles"
                ]
            },
            "arcane": {
                "mana": 10000,
                "int": 30,
                "maint": 50,
                "effect": [
                    "SR 30",
                    "No spacial limit"
                ]
            }
        }
    },
    {
        "name": "The Gift of Life",
        "type": "path",
        "level": 98,
        "power": [
            "automatic"
        ],
        "action": "active",
        "maintTime": "turn",
        "tags": [],
        "description": [
            "You create a new form of life. The life forms's maximum level is listed and follows the rules for creatures created by powers. Additionally, the following rules apply:",
            {
                "type": "list",
                "items": [
                    "The creature is either a natural, spiritual or Beyond the Veil creature.",
                    "The creature's Nornir can be any value you choose, but can be no greater than ten points below your Nornir.",
                    ""
                ]
            },
            "You can choose wether the new creature will be one that is part of the Veil. If you do, it becomes a true part of the world and it will start to appear in an a natural habitat for it, can be summoned, or might even appear as part of the next Veil -- depending on the creature type.",
            "When the spell ends, all life forms disappear even those that were born naturally. The souls of these creatures do not return to the Veil, and instead disappear completely."
        ],
        "degree": {
            "base": {
                "mana": 800,
                "int": 16,
                "maint": 30,
                "effect": [
                    "Level 1"
                ]
            },
            "intermediate": {
                "mana": 2000,
                "int": 20,
                "maint": 40,
                "effect": [
                    "Level 6"
                ]
            },
            "advanced": {
                "mana": 4000,
                "int": 24,
                "maint": 45,
                "effect": [
                    "Level 11"
                ]
            },
            "arcane": {
                "mana": 8000,
                "int": 30,
                "maint": 50,
                "effect": [
                    "Level 16"
                ]
            }
        }
    },
    {
        "name": "Create",
        "type": "path",
        "level": 100,
        "power": [
            "automatic"
        ],
        "action": "active",
        "maintTime": "no",
        "tags": [],
        "description": [
            "You gain absolute control over creation. You gain a pool of Presence Points that you can use to create anything; continents, oceans, and entire worlds can be created by your hand. Any entity you create cannot have a Presence greater than the listed maximum Presence. Additionally, you can impose new rules upon reality. For example, you can change the fundamental law of gravity or the passage of time. Any creature with a Nornir of less than half your Nornir is affected by the new reality.",
            "The Presence you can create with allows you to create new worlds even"
        ],
        "degree": {
            "base": {
                "mana": 1000,
                "int": 20,
                "maint": 0,
                "effect": [
                    "100 Presence Points",
                    "Max Presence 20",
                    "1 rule"
                ]
            },
            "intermediate": {
                "mana": 3000,
                "int": 24,
                "maint": 0,
                "effect": [
                    "1000 Presence Points",
                    "Max Presence 40",
                    "5 rules"
                ]
            },
            "advanced": {
                "mana": 6000,
                "int": 28,
                "maint": 0,
                "effect": [
                    "10000 Presence Points",
                    "Max Presence 80",
                    "10 rules"
                ]
            },
            "arcane": {
                "mana": 12000,
                "int": 36,
                "maint": 0,
                "effect": [
                    "100000 Presence Points",
                    "Max Presence 160",
                    "Any number of rules"
                ]
            }
        }
    }
]